Metadata-Version: 2.1
Name: easy-environment
Version: 0.1
Summary: A library to set environment variables using shell rc files
Home-page: https://github.com/ltanedo/easy-environment.git
Author: lloydtan
Author-email: lloydtan@buffalo.edu
License: MIT
Download-URL: https://github.com/ltanedo/easy-environment/archive/refs/tags/v_01.tar.gz
Keywords: python,env,environment
Platform: UNKNOWN
Classifier: Development Status :: 3 - Alpha
Classifier: Intended Audience :: Developers
Classifier: Topic :: Software Development :: Build Tools
Classifier: License :: OSI Approved :: MIT License
Classifier: Programming Language :: Python :: 3
Classifier: Programming Language :: Python :: 3.4
Classifier: Programming Language :: Python :: 3.5
Classifier: Programming Language :: Python :: 3.6
Classifier: Programming Language :: Python :: 3.8
License-File: LICENSE.txt
